error_visor/__init__.py
error_visor/logger.py
error_visor-0.0.6.dist-info/METADATA
error_visor-0.0.6.dist-info/WHEEL
error_visor-0.0.6.dist-info/top_level.txt
error_visor-0.0.6.dist-info/RECORD
