Metadata-Version: 2.1
Name: error-visor
Version: 0.0.6
Summary: Librería para guardar registros de errores y warnings personalizados en json
Home-page: https://github.com/vvalenzuela96/error_visor_project
Author: Victor Valenzuela M
Author-email: vi.valenzuelam@gmail.com
License: MIT
